{
  "routes": [
    {
      "method": "GET",
      "path": "/managers",
      "handler": "managers.find",
      "config": {
        "policies": []
      }
    },
    {
      "method": "GET",
      "path": "/managers/count",
      "handler": "managers.count",
      "config": {
        "policies": []
      }
    },
    {
      "method": "GET",
      "path": "/managers/:id",
      "handler": "managers.findOne",
      "config": {
        "policies": []
      }
    },
    {
      "method": "POST",
      "path": "/managers",
      "handler": "managers.create",
      "config": {
        "policies": []
      }
    },
    {
      "method": "PUT",
      "path": "/managers/:id",
      "handler": "managers.update",
      "config": {
        "policies": []
      }
    },
    {
      "method": "DELETE",
      "path": "/managers/:id",
      "handler": "managers.delete",
      "config": {
        "policies": []
      }
    }
  ]
}
